{
    "Бюджетных мест": 5,
    "Направление": "45.03.02 Прикладная, компьютерная и математическая лингвистика (английский язык)",
    "Конкурс": {
        "170-960-635 77": {
            "Приоритет": 1,
            "Место в списке": 1,
            "Без ВИ": true,
            "Баллы": 3
        },
        "170-544-543 56": {
            "Приоритет": 1,
            "Место в списке": 2,
            "Без ВИ": false,
            "Баллы": 298
        },
        "164-789-817 34": {
            "Приоритет": 3,
            "Место в списке": 3,
            "Без ВИ": false,
            "Баллы": 297
        },
        "186-762-002 96": {
            "Приоритет": 1,
            "Место в списке": 4,
            "Без ВИ": false,
            "Баллы": 294
        },
        "168-445-513 96": {
            "Приоритет": 2,
            "Место в списке": 5,
            "Без ВИ": false,
            "Баллы": 291
        },
        "162-787-200 86": {
            "Приоритет": 2,
            "Место в списке": 6,
            "Без ВИ": false,
            "Баллы": 290
        },
        "159-010-320 29": {
            "Приоритет": 5,
            "Место в списке": 7,
            "Без ВИ": false,
            "Баллы": 290
        },
        "160-632-041 24": {
            "Приоритет": 5,
            "Место в списке": 8,
            "Без ВИ": false,
            "Баллы": 289
        },
        "170-206-402 14": {
            "Приоритет": 4,
            "Место в списке": 9,
            "Без ВИ": false,
            "Баллы": 284
        },
        "161-615-914 57": {
            "Приоритет": 6,
            "Место в списке": 10,
            "Без ВИ": false,
            "Баллы": 283
        },
        "168-961-837 36": {
            "Приоритет": 13,
            "Место в списке": 11,
            "Без ВИ": false,
            "Баллы": 283
        },
        "164-198-121 75": {
            "Приоритет": 24,
            "Место в списке": 12,
            "Без ВИ": false,
            "Баллы": 280
        },
        "166-405-211 51": {
            "Приоритет": 1,
            "Место в списке": 13,
            "Без ВИ": false,
            "Баллы": 279
        },
        "186-734-359 14": {
            "Приоритет": 1,
            "Место в списке": 14,
            "Без ВИ": false,
            "Баллы": 279
        },
        "196-765-892 57": {
            "Приоритет": 5,
            "Место в списке": 15,
            "Без ВИ": false,
            "Баллы": 279
        },
        "171-043-879 50": {
            "Приоритет": 1,
            "Место в списке": 16,
            "Без ВИ": false,
            "Баллы": 278
        },
        "168-922-323 00": {
            "Приоритет": 4,
            "Место в списке": 17,
            "Без ВИ": false,
            "Баллы": 278
        },
        "201-316-006 78": {
            "Приоритет": 19,
            "Место в списке": 18,
            "Без ВИ": false,
            "Баллы": 277
        },
        "164-436-063 62": {
            "Приоритет": 15,
            "Место в списке": 19,
            "Без ВИ": false,
            "Баллы": 276
        },
        "158-703-032 66": {
            "Приоритет": 18,
            "Место в списке": 20,
            "Без ВИ": false,
            "Баллы": 276
        },
        "156-728-512 93": {
            "Приоритет": 8,
            "Место в списке": 21,
            "Без ВИ": false,
            "Баллы": 275
        },
        "167-003-840 49": {
            "Приоритет": 2,
            "Место в списке": 22,
            "Без ВИ": false,
            "Баллы": 275
        },
        "160-115-503 05": {
            "Приоритет": 2,
            "Место в списке": 23,
            "Без ВИ": false,
            "Баллы": 274
        },
        "175-518-707 94": {
            "Приоритет": 4,
            "Место в списке": 24,
            "Без ВИ": false,
            "Баллы": 274
        },
        "172-425-419 55": {
            "Приоритет": 1,
            "Место в списке": 25,
            "Без ВИ": false,
            "Баллы": 274
        },
        "169-100-547 55": {
            "Приоритет": 2,
            "Место в списке": 26,
            "Без ВИ": false,
            "Баллы": 273
        },
        "150-262-720 23": {
            "Приоритет": 2,
            "Место в списке": 27,
            "Без ВИ": false,
            "Баллы": 271
        },
        "183-590-881 08": {
            "Приоритет": 5,
            "Место в списке": 28,
            "Без ВИ": false,
            "Баллы": 271
        },
        "170-700-664 40": {
            "Приоритет": 5,
            "Место в списке": 29,
            "Без ВИ": false,
            "Баллы": 271
        },
        "185-931-552 06": {
            "Приоритет": 3,
            "Место в списке": 30,
            "Без ВИ": false,
            "Баллы": 270
        },
        "156-728-608 00": {
            "Приоритет": 3,
            "Место в списке": 31,
            "Без ВИ": false,
            "Баллы": 270
        },
        "165-682-294 02": {
            "Приоритет": 7,
            "Место в списке": 32,
            "Без ВИ": false,
            "Баллы": 270
        },
        "161-024-770 24": {
            "Приоритет": 21,
            "Место в списке": 33,
            "Без ВИ": false,
            "Баллы": 270
        },
        "174-173-886 91": {
            "Приоритет": 1,
            "Место в списке": 34,
            "Без ВИ": false,
            "Баллы": 269
        },
        "204-763-136 44": {
            "Приоритет": 4,
            "Место в списке": 35,
            "Без ВИ": false,
            "Баллы": 269
        },
        "207-674-027 64": {
            "Приоритет": 3,
            "Место в списке": 36,
            "Без ВИ": false,
            "Баллы": 268
        },
        "198-579-147 54": {
            "Приоритет": 13,
            "Место в списке": 37,
            "Без ВИ": false,
            "Баллы": 268
        },
        "166-405-357 68": {
            "Приоритет": 5,
            "Место в списке": 38,
            "Без ВИ": false,
            "Баллы": 266
        },
        "184-208-802 70": {
            "Приоритет": 7,
            "Место в списке": 39,
            "Без ВИ": false,
            "Баллы": 266
        },
        "175-269-354 00": {
            "Приоритет": 3,
            "Место в списке": 40,
            "Без ВИ": false,
            "Баллы": 265
        },
        "164-253-741 63": {
            "Приоритет": 21,
            "Место в списке": 41,
            "Без ВИ": false,
            "Баллы": 264
        },
        "140-632-185 23": {
            "Приоритет": 17,
            "Место в списке": 42,
            "Без ВИ": false,
            "Баллы": 262
        },
        "158-046-581 80": {
            "Приоритет": 5,
            "Место в списке": 43,
            "Без ВИ": false,
            "Баллы": 262
        },
        "189-917-445 46": {
            "Приоритет": 8,
            "Место в списке": 44,
            "Без ВИ": false,
            "Баллы": 262
        },
        "164-495-529 00": {
            "Приоритет": 1,
            "Место в списке": 45,
            "Без ВИ": false,
            "Баллы": 261
        },
        "173-727-603 86": {
            "Приоритет": 6,
            "Место в списке": 46,
            "Без ВИ": false,
            "Баллы": 261
        },
        "163-834-104 63": {
            "Приоритет": 3,
            "Место в списке": 47,
            "Без ВИ": false,
            "Баллы": 261
        },
        "167-964-060 16": {
            "Приоритет": 2,
            "Место в списке": 48,
            "Без ВИ": false,
            "Баллы": 260
        },
        "174-721-494 82": {
            "Приоритет": 4,
            "Место в списке": 49,
            "Без ВИ": false,
            "Баллы": 259
        },
        "173-504-081 48": {
            "Приоритет": 5,
            "Место в списке": 50,
            "Без ВИ": false,
            "Баллы": 259
        },
        "161-507-966 66": {
            "Приоритет": 4,
            "Место в списке": 51,
            "Без ВИ": false,
            "Баллы": 259
        },
        "204-924-241 40": {
            "Приоритет": 2,
            "Место в списке": 52,
            "Без ВИ": false,
            "Баллы": 259
        },
        "148-579-042 06": {
            "Приоритет": 18,
            "Место в списке": 53,
            "Без ВИ": false,
            "Баллы": 258
        },
        "189-731-510 12": {
            "Приоритет": 5,
            "Место в списке": 54,
            "Без ВИ": false,
            "Баллы": 257
        },
        "162-439-556 76": {
            "Приоритет": 8,
            "Место в списке": 55,
            "Без ВИ": false,
            "Баллы": 257
        },
        "166-073-426 67": {
            "Приоритет": 1,
            "Место в списке": 56,
            "Без ВИ": false,
            "Баллы": 256
        },
        "166-795-460 28": {
            "Приоритет": 8,
            "Место в списке": 57,
            "Без ВИ": false,
            "Баллы": 256
        },
        "194-644-143 94": {
            "Приоритет": 1,
            "Место в списке": 58,
            "Без ВИ": false,
            "Баллы": 255
        },
        "169-751-621 12": {
            "Приоритет": 11,
            "Место в списке": 59,
            "Без ВИ": false,
            "Баллы": 255
        },
        "169-758-996 68": {
            "Приоритет": 3,
            "Место в списке": 60,
            "Без ВИ": false,
            "Баллы": 253
        },
        "170-632-113 31": {
            "Приоритет": 7,
            "Место в списке": 61,
            "Без ВИ": false,
            "Баллы": 250
        },
        "168-702-917 98": {
            "Приоритет": 6,
            "Место в списке": 62,
            "Без ВИ": false,
            "Баллы": 245
        },
        "158-992-909 46": {
            "Приоритет": 1,
            "Место в списке": 63,
            "Без ВИ": false,
            "Баллы": 241
        },
        "209-134-825 50": {
            "Приоритет": 10,
            "Место в списке": 64,
            "Без ВИ": false,
            "Баллы": 235
        },
        "157-858-430 19": {
            "Приоритет": 15,
            "Место в списке": 65,
            "Без ВИ": false,
            "Баллы": 234
        },
        "144-264-189 54": {
            "Приоритет": 7,
            "Место в списке": 66,
            "Без ВИ": false,
            "Баллы": 222
        },
        "138-627-104 69": {
            "Приоритет": 2,
            "Место в списке": 67,
            "Без ВИ": false,
            "Баллы": 191
        },
        "168-810-405 82": {
            "Приоритет": 2,
            "Место в списке": 68,
            "Без ВИ": false,
            "Баллы": 176
        },
        "178-016-001 50": {
            "Приоритет": 1,
            "Место в списке": 69,
            "Без ВИ": false,
            "Баллы": 170
        },
        "185-673-007 97": {
            "Приоритет": 2,
            "Место в списке": 70,
            "Без ВИ": false,
            "Баллы": 169
        },
        "199-631-220 07": {
            "Приоритет": 29,
            "Место в списке": 71,
            "Без ВИ": false,
            "Баллы": 91
        },
        "160-965-275 85": {
            "Приоритет": 10,
            "Место в списке": 72,
            "Без ВИ": false,
            "Баллы": 79
        },
        "174-770-574 01": {
            "Приоритет": 4,
            "Место в списке": 73,
            "Без ВИ": false,
            "Баллы": 3
        },
        "165-433-271 63": {
            "Приоритет": 12,
            "Место в списке": 74,
            "Без ВИ": false,
            "Баллы": 3
        },
        "166-903-826 98": {
            "Приоритет": 9,
            "Место в списке": 75,
            "Без ВИ": false,
            "Баллы": 0
        },
        "166-066-806 82": {
            "Приоритет": 19,
            "Место в списке": 76,
            "Без ВИ": false,
            "Баллы": 0
        },
        "166-903-971 05": {
            "Приоритет": 9,
            "Место в списке": 77,
            "Без ВИ": false,
            "Баллы": 0
        },
        "23088506": {
            "Приоритет": 2,
            "Место в списке": 78,
            "Без ВИ": false,
            "Баллы": 0
        },
        "180-516-829 68": {
            "Приоритет": 8,
            "Место в списке": 79,
            "Без ВИ": false,
            "Баллы": 0
        },
        "136-260-823 47": {
            "Приоритет": 5,
            "Место в списке": 80,
            "Без ВИ": false,
            "Баллы": 0
        },
        "165-492-426 90": {
            "Приоритет": 5,
            "Место в списке": 81,
            "Без ВИ": false,
            "Баллы": 0
        },
        "190-677-107 89": {
            "Приоритет": 1,
            "Место в списке": 82,
            "Без ВИ": false,
            "Баллы": 0
        },
        "209-122-787 48": {
            "Приоритет": 10,
            "Место в списке": 83,
            "Без ВИ": false,
            "Баллы": 0
        },
        "182-571-149 75": {
            "Приоритет": 5,
            "Место в списке": 84,
            "Без ВИ": false,
            "Баллы": 0
        },
        "176-530-644 81": {
            "Приоритет": 3,
            "Место в списке": 85,
            "Без ВИ": false,
            "Баллы": 0
        },
        "157-973-863 36": {
            "Приоритет": 7,
            "Место в списке": 86,
            "Без ВИ": false,
            "Баллы": 0
        },
        "178-640-741 05": {
            "Приоритет": 8,
            "Место в списке": 87,
            "Без ВИ": false,
            "Баллы": 0
        },
        "166-292-324 80": {
            "Приоритет": 8,
            "Место в списке": 88,
            "Без ВИ": false,
            "Баллы": 0
        },
        "209-402-294 40": {
            "Приоритет": 3,
            "Место в списке": 89,
            "Без ВИ": false,
            "Баллы": 0
        },
        "141-449-268 53": {
            "Приоритет": 1,
            "Место в списке": 90,
            "Без ВИ": false,
            "Баллы": 0
        },
        "166-180-241 59": {
            "Приоритет": 15,
            "Место в списке": 91,
            "Без ВИ": false,
            "Баллы": 0
        },
        "198-514-633 13": {
            "Приоритет": 13,
            "Место в списке": 92,
            "Без ВИ": false,
            "Баллы": 0
        },
        "160-460-165 30": {
            "Приоритет": 17,
            "Место в списке": 93,
            "Без ВИ": false,
            "Баллы": 0
        },
        "166-951-342 00": {
            "Приоритет": 5,
            "Место в списке": 94,
            "Без ВИ": false,
            "Баллы": 0
        },
        "208-772-853 95": {
            "Приоритет": 17,
            "Место в списке": 95,
            "Без ВИ": false,
            "Баллы": 0
        },
        "163-926-913 97": {
            "Приоритет": 12,
            "Место в списке": 96,
            "Без ВИ": false,
            "Баллы": 0
        },
        "153-032-461 17": {
            "Приоритет": 4,
            "Место в списке": 97,
            "Без ВИ": false,
            "Баллы": 0
        }
    }
}